MANIFEST.in
README.md
setup.py
txtwrap/__init__.py
txtwrap/__init__.pyi
txtwrap/_utils.py
txtwrap/constants.py
txtwrap/constants.pyi
txtwrap/identities.py
txtwrap/identities.pyi
txtwrap/wrapper.py
txtwrap/wrapper.pyi
txtwrap.egg-info/PKG-INFO
txtwrap.egg-info/SOURCES.txt
txtwrap.egg-info/dependency_links.txt
txtwrap.egg-info/top_level.txt