Metadata-Version: 2.4
Name: txtwrap
Version: 3.1.0
Summary: A tool for wrapping and filling text.
Home-page: https://github.com/azzammuhyala/txtwrap
Author: azzammuhyala
Author-email: azzammuhyala@gmail.com
License: MIT
Project-URL: Source, https://github.com/azzammuhyala/txtwrap
Project-URL: Bug Tracker, https://github.com/azzammuhyala/txtwrap/issues
Keywords: wrap,wrapper,wrapping,wrapped,text wrap,text wrapper,text wrapping,text wrapped
Classifier: Programming Language :: Python
Classifier: Programming Language :: Python :: 3
Classifier: Topic :: Software Development :: Libraries :: Python Modules
Classifier: Topic :: Text Processing
Classifier: Topic :: Text Processing :: Filters
Requires-Python: >=3.0
Dynamic: author
Dynamic: author-email
Dynamic: classifier
Dynamic: description
Dynamic: description-content-type
Dynamic: home-page
Dynamic: keywords
Dynamic: license
Dynamic: project-url
Dynamic: requires-python
Dynamic: summary
